{
    "Materials": [],
    "NotUseDfonSubstrate": true,
    "DefaultDF": 0.02,
    "OpenInAedt": true,
    "IgnoreLayersReg": [
        "air",
        "ctm.*",
        "cbm.*",
        "dtce.*"
    ],
    "ImportDummyNet": true,
    "LayerMapFile": null,
    "ControlXmlPath": null,
    "InputType": 0,
    "CompLayerList": [
        1,
        -1
    ],
    "ThinDielectricThreshold": 0.10000000000000001,
    "UseDefaultDF": false,
    "MergeDielectricMethod": 0,
    "Default": null,
    "InsulatorThickness": 1,
    "AutoTSVCoat": true,
    "DissolveViaGroup": true,
    "Precision": 6,
    "GdsFile": null,
    "edbPath": null,
    "UseTemperatureDependMaterial": false,
    "CreatViaGroups": true,
    "TechFile": null,
    "UseShortMergeLayerName": true,
    "AedtInstallDir": null,
    "DkDeviationThreshold": 0.050000000000000003,
    "TextLayermap": {},
    "UseSheetLayer": true,
    "FixedSmallLayerGap": 0.0050000000000000001,
    "SheetLayerThreshold": 0.0015,
    "NetRegular": ".*",
    "NetlistFile": null,
    "AutoComps": true,
    "SimplifyDieletricMethod": 1
}